{
  "minecraft:recipes/decorations/crafting_table": {
    "criteria": {
      "unlock_right_away": "2024-09-03 15:37:31 +1000"
    },
    "done": true
  },
  "minecraft:adventure/adventuring_time": {
    "criteria": {
      "minecraft:plains": "2024-09-03 15:37:34 +1000"
    },
    "done": false
  },
  "aether:recipes/misc/flower_to_purple_dye": {
    "criteria": {
      "has_purple_flower": "2024-09-03 15:37:47 +1000"
    },
    "done": true
  },
  "aether:recipes/misc/flower_to_white_dye": {
    "criteria": {
      "has_white_flower": "2024-09-03 15:37:48 +1000"
    },
    "done": true
  },
  "minecraft:recipes/redstone/redstone_lamp": {
    "criteria": {
      "has_glowstone": "2024-09-03 15:38:20 +1000"
    },
    "done": true
  },
  "aether:recipes/building_blocks/packed_ice_freezing": {
    "criteria": {
      "has_water_bucket": "2024-09-03 15:38:24 +1000"
    },
    "done": true
  },
  "aether:recipes/building_blocks/blue_ice_freezing": {
    "criteria": {
      "has_water_bucket": "2024-09-03 15:38:24 +1000"
    },
    "done": true
  },
  "aether:recipes/building_blocks/ice_from_bucket_freezing": {
    "criteria": {
      "has_water_bucket": "2024-09-03 15:38:24 +1000"
    },
    "done": true
  },
  "minecraft:recipes/brewing/cauldron": {
    "criteria": {
      "has_water_bucket": "2024-09-03 15:38:24 +1000"
    },
    "done": true
  },
  "aether:recipes/transportation/skyroot_boat": {
    "criteria": {
      "in_water": "2024-09-03 15:38:26 +1000"
    },
    "done": true
  },
  "minecraft:recipes/transportation/cherry_boat": {
    "criteria": {
      "in_water": "2024-09-03 15:38:26 +1000"
    },
    "done": true
  },
  "minecraft:recipes/transportation/bamboo_raft": {
    "criteria": {
      "in_water": "2024-09-03 15:38:26 +1000"
    },
    "done": true
  },
  "minecraft:recipes/transportation/spruce_boat": {
    "criteria": {
      "in_water": "2024-09-03 15:38:26 +1000"
    },
    "done": true
  },
  "minecraft:recipes/transportation/birch_boat": {
    "criteria": {
      "in_water": "2024-09-03 15:38:26 +1000"
    },
    "done": true
  },
  "minecraft:recipes/transportation/oak_boat": {
    "criteria": {
      "in_water": "2024-09-03 15:38:26 +1000"
    },
    "done": true
  },
  "minecraft:recipes/transportation/mangrove_boat": {
    "criteria": {
      "in_water": "2024-09-03 15:38:26 +1000"
    },
    "done": true
  },
  "minecraft:recipes/transportation/acacia_boat": {
    "criteria": {
      "in_water": "2024-09-03 15:38:26 +1000"
    },
    "done": true
  },
  "minecraft:recipes/transportation/jungle_boat": {
    "criteria": {
      "in_water": "2024-09-03 15:38:26 +1000"
    },
    "done": true
  },
  "minecraft:recipes/transportation/dark_oak_boat": {
    "criteria": {
      "in_water": "2024-09-03 15:38:26 +1000"
    },
    "done": true
  },
  "aether:recipes/tools/diamond_hoe_repairing": {
    "criteria": {
      "has_diamond_hoe": "2024-09-03 16:07:05 +1000"
    },
    "done": true
  },
  "minecraft:recipes/misc/white_dye": {
    "criteria": {
      "has_bone_meal": "2024-09-03 16:07:14 +1000"
    },
    "done": true
  },
  "minecraft:recipes/building_blocks/bone_block": {
    "criteria": {
      "has_bone_meal": "2024-09-03 16:07:14 +1000"
    },
    "done": true
  },
  "DataVersion": 3700
}